<?xml version="1.0" encoding="UTF-8" standalone="yes"?>
<idPkg:Story xmlns:idPkg="http://ns.adobe.com/AdobeInDesign/idml/1.0/packaging" DOMVersion="13.0">
	<Story Self="u2c5" IsEndnoteStory="false" UserText="true" AppliedTOCStyle="n" StoryTitle="$ID/" TrackChanges="false" AppliedNamedGrid="n">
		<StoryPreference OpticalMarginAlignment="false" OpticalMarginSize="12" FrameType="TextFrameType" StoryOrientation="Horizontal" StoryDirection="LeftToRightDirection" />
		<InCopyExportOption IncludeGraphicProxies="true" IncludeAllResources="false" />
		<ParagraphStyleRange AppliedParagraphStyle="ParagraphStyle/Heading">
			<CharacterStyleRange AppliedCharacterStyle="CharacterStyle/$ID/[No character style]">
				<Content>Service</Content>
				<Br />
			</CharacterStyleRange>
		</ParagraphStyleRange>
		<ParagraphStyleRange AppliedParagraphStyle="ParagraphStyle/First Paragraph">
			<CharacterStyleRange AppliedCharacterStyle="CharacterStyle/$ID/[No character style]">
				<Content>The </Content>
			</CharacterStyleRange>
			<CharacterStyleRange AppliedCharacterStyle="CharacterStyle/$ID/[No character style]" FontStyle="Italic">
				<Content>Student Advisory Committee</Content>
			</CharacterStyleRange>
			<CharacterStyleRange AppliedCharacterStyle="CharacterStyle/$ID/[No character style]">
				<Content> is a group of undergraduates who advise the board of directors of ΛΧΑ. Seven Sigma brothers have served on this committee:</Content>
				<Br />
			</CharacterStyleRange>
		</ParagraphStyleRange>
		<ParagraphStyleRange AppliedParagraphStyle="ParagraphStyle/Name">
			<CharacterStyleRange AppliedCharacterStyle="CharacterStyle/$ID/[No character style]">
				<Content>Roger T. Whitaker ’73	</Content>
			</CharacterStyleRange>
			<CharacterStyleRange AppliedCharacterStyle="CharacterStyle/$ID/[No character style]" OTFFigureStyle="TabularOldstyle">
				<Content>1971–1973</Content>
			</CharacterStyleRange>
			<CharacterStyleRange AppliedCharacterStyle="CharacterStyle/$ID/[No character style]">
				<Br />
				<Content>Bruce L. Koepfgen ’74	</Content>
			</CharacterStyleRange>
			<CharacterStyleRange AppliedCharacterStyle="CharacterStyle/$ID/[No character style]" OTFFigureStyle="TabularOldstyle">
				<Content>1973–1974</Content>
			</CharacterStyleRange>
			<CharacterStyleRange AppliedCharacterStyle="CharacterStyle/$ID/[No character style]">
				<Br />
				<Content>Louis J. Leonardi ’76	</Content>
			</CharacterStyleRange>
			<CharacterStyleRange AppliedCharacterStyle="CharacterStyle/$ID/[No character style]" OTFFigureStyle="TabularOldstyle">
				<Content>1975–1976</Content>
			</CharacterStyleRange>
			<CharacterStyleRange AppliedCharacterStyle="CharacterStyle/$ID/[No character style]">
				<Br />
				<Content>Steven M. Scheidt ’79	</Content>
			</CharacterStyleRange>
			<CharacterStyleRange AppliedCharacterStyle="CharacterStyle/$ID/[No character style]" OTFFigureStyle="TabularOldstyle">
				<Content>1978–1979</Content>
			</CharacterStyleRange>
			<CharacterStyleRange AppliedCharacterStyle="CharacterStyle/$ID/[No character style]">
				<Br />
				<Content>Ethan A. Rein ’07	</Content>
			</CharacterStyleRange>
			<CharacterStyleRange AppliedCharacterStyle="CharacterStyle/$ID/[No character style]" OTFFigureStyle="TabularOldstyle">
				<Content>2006–2007</Content>
			</CharacterStyleRange>
			<CharacterStyleRange AppliedCharacterStyle="CharacterStyle/$ID/[No character style]">
				<Br />
				<Content>Christopher K. VanDeusen ’08	</Content>
			</CharacterStyleRange>
			<CharacterStyleRange AppliedCharacterStyle="CharacterStyle/$ID/[No character style]" OTFFigureStyle="TabularOldstyle">
				<Content>2007–2008</Content>
			</CharacterStyleRange>
			<CharacterStyleRange AppliedCharacterStyle="CharacterStyle/$ID/[No character style]">
				<Br />
				<Content>Brian M. Verkinderen ’14	</Content>
			</CharacterStyleRange>
			<CharacterStyleRange AppliedCharacterStyle="CharacterStyle/$ID/[No character style]" OTFFigureStyle="TabularOldstyle">
				<Content>2012–2013</Content>
			</CharacterStyleRange>
			<CharacterStyleRange AppliedCharacterStyle="CharacterStyle/$ID/[No character style]">
				<Br />
			</CharacterStyleRange>
		</ParagraphStyleRange>
		<ParagraphStyleRange AppliedParagraphStyle="ParagraphStyle/First Paragraph">
			<CharacterStyleRange AppliedCharacterStyle="CharacterStyle/$ID/[No character style]">
				<Br />
				<Content>The </Content>
			</CharacterStyleRange>
			<CharacterStyleRange AppliedCharacterStyle="CharacterStyle/$ID/[No character style]" FontStyle="Italic">
				<Content>Alumni Advisory Committee</Content>
			</CharacterStyleRange>
			<CharacterStyleRange AppliedCharacterStyle="CharacterStyle/$ID/[No character style]">
				<Content>, created at the 1970 General Assembly, advises the board of directors of ΛΧΑ. From 1970–1974, J. William Schepers ’60 served on this committee.</Content>
				<Br />
				<Br />
				<Content>The </Content>
			</CharacterStyleRange>
			<CharacterStyleRange AppliedCharacterStyle="CharacterStyle/$ID/[No character style]" FontStyle="Italic">
				<Content>Lambda Chi Alpha Educational Foundation</Content>
			</CharacterStyleRange>
			<CharacterStyleRange AppliedCharacterStyle="CharacterStyle/$ID/[No character style]">
				<Content> raises money for educational programming like the Stead Leadership Seminar and TRUE Brother Initiative. Charles W. Cole ’73 serves on its board of directors.</Content>
				<Br />
				<Br />
				<Content>The </Content>
			</CharacterStyleRange>
			<CharacterStyleRange AppliedCharacterStyle="CharacterStyle/$ID/[No character style]" FontStyle="Italic">
				<Content>Professional Staff</Content>
			</CharacterStyleRange>
			<CharacterStyleRange AppliedCharacterStyle="CharacterStyle/$ID/[No character style]">
				<Content> perform the day-to-day operations of ΛΧΑ. Three Sigma brothers have served on the Professional Staff:</Content>
				<Br />
			</CharacterStyleRange>
		</ParagraphStyleRange>
		<ParagraphStyleRange AppliedParagraphStyle="ParagraphStyle/Name">
			<CharacterStyleRange AppliedCharacterStyle="CharacterStyle/$ID/[No character style]">
				<Content>George W. Spasyk ’49	</Content>
			</CharacterStyleRange>
			<CharacterStyleRange AppliedCharacterStyle="CharacterStyle/$ID/[No character style]" OTFFigureStyle="TabularOldstyle">
				<Content>1950–1990</Content>
			</CharacterStyleRange>
			<CharacterStyleRange AppliedCharacterStyle="CharacterStyle/$ID/[No character style]">
				<Br />
				<Content>J. William Schepers ’60	</Content>
			</CharacterStyleRange>
			<CharacterStyleRange AppliedCharacterStyle="CharacterStyle/$ID/[No character style]" OTFFigureStyle="TabularOldstyle">
				<Content>1960–1961</Content>
			</CharacterStyleRange>
			<CharacterStyleRange AppliedCharacterStyle="CharacterStyle/$ID/[No character style]">
				<Br />
				<Content>Gregory L. Jones ’78	</Content>
			</CharacterStyleRange>
			<CharacterStyleRange AppliedCharacterStyle="CharacterStyle/$ID/[No character style]" OTFFigureStyle="TabularOldstyle">
				<Content>1978–1979</Content>
			</CharacterStyleRange>
			<CharacterStyleRange AppliedCharacterStyle="CharacterStyle/$ID/[No character style]">
				<Br />
			</CharacterStyleRange>
		</ParagraphStyleRange>
		<ParagraphStyleRange AppliedParagraphStyle="ParagraphStyle/First Paragraph">
			<CharacterStyleRange AppliedCharacterStyle="CharacterStyle/$ID/[No character style]">
				<Content>Brother Spasyk was Executive Director of ΛΧΑ from 1968–1990.</Content>
				<Br />
				<Br />
				<Content>While a student at the University of Michigan, Wilbur J. Perry ’49 rearranged the </Content>
			</CharacterStyleRange>
			<CharacterStyleRange AppliedCharacterStyle="CharacterStyle/$ID/[No character style]" FontStyle="Italic">
				<Content>Lambda Chi Alpha Songbook</Content>
			</CharacterStyleRange>
			<CharacterStyleRange AppliedCharacterStyle="CharacterStyle/$ID/[No character style]">
				<Content>. His arrangements remain in use today all over North America.</Content>
			</CharacterStyleRange>
		</ParagraphStyleRange>
	</Story>
</idPkg:Story>
