<?xml version="1.0" encoding="UTF-8" standalone="yes"?>
<idPkg:Story xmlns:idPkg="http://ns.adobe.com/AdobeInDesign/idml/1.0/packaging" DOMVersion="13.0">
	<Story Self="u394" IsEndnoteStory="false" UserText="true" AppliedTOCStyle="n" StoryTitle="$ID/" TrackChanges="false" AppliedNamedGrid="n">
		<StoryPreference OpticalMarginAlignment="false" OpticalMarginSize="12" FrameType="TextFrameType" StoryOrientation="Horizontal" StoryDirection="LeftToRightDirection" />
		<InCopyExportOption IncludeGraphicProxies="true" IncludeAllResources="false" />
		<ParagraphStyleRange AppliedParagraphStyle="ParagraphStyle/Heading">
			<CharacterStyleRange AppliedCharacterStyle="CharacterStyle/$ID/[No character style]">
				<Content>Program</Content>
				<Br />
			</CharacterStyleRange>
		</ParagraphStyleRange>
		<ParagraphStyleRange AppliedParagraphStyle="ParagraphStyle/Program Item">
			<CharacterStyleRange AppliedCharacterStyle="CharacterStyle/$ID/[No character style]">
				<Br />
				<Content>Fellowship</Content>
				<Br />
				<Br />
				<Br />
				<Content>Invocation</Content>
				<Br />
			</CharacterStyleRange>
			<CharacterStyleRange AppliedCharacterStyle="CharacterStyle/$ID/[No character style]" FontStyle="Italic">
				<Content>Clarence L. Pozza, Jr.</Content>
				<Br />
			</CharacterStyleRange>
			<CharacterStyleRange AppliedCharacterStyle="CharacterStyle/$ID/[No character style]">
				<Br />
				<Br />
				<Content>Dinner</Content>
				<Br />
				<Br />
				<Br />
				<Content>Introduction of Guests</Content>
				<Br />
				<Br />
				<Content>Brotherhood Countdown</Content>
				<Br />
				<Br />
				<Content>Academic Awards</Content>
				<Br />
			</CharacterStyleRange>
			<CharacterStyleRange AppliedCharacterStyle="CharacterStyle/$ID/[No character style]" FontStyle="Italic">
				<Content>Andrew L. Knowlton, President, Sigma Alumni Association</Content>
			</CharacterStyleRange>
			<CharacterStyleRange AppliedCharacterStyle="CharacterStyle/$ID/[No character style]">
				<Br />
				<Br />
				<Br />
				<Content>University Remarks</Content>
				<Br />
			</CharacterStyleRange>
			<CharacterStyleRange AppliedCharacterStyle="CharacterStyle/$ID/[No character style]" FontStyle="Italic">
				<Content>Mary Beth Seiler, Director, Office of Greek Life</Content>
				<Br />
			</CharacterStyleRange>
			<CharacterStyleRange AppliedCharacterStyle="CharacterStyle/$ID/[No character style]">
				<Br />
				<Content>Undergraduate Remarks</Content>
				<Br />
			</CharacterStyleRange>
			<CharacterStyleRange AppliedCharacterStyle="CharacterStyle/$ID/[No character style]" FontStyle="Italic">
				<Content>Rex Zhou, Chapter President</Content>
				<Br />
			</CharacterStyleRange>
			<CharacterStyleRange AppliedCharacterStyle="CharacterStyle/$ID/[No character style]">
				<Br />
				<Content>Keynote Address</Content>
				<Br />
			</CharacterStyleRange>
			<CharacterStyleRange AppliedCharacterStyle="CharacterStyle/$ID/[No character style]" FontStyle="Italic">
				<Content>Dr. Murphy M. Osborne, Former Grand High Alpha</Content>
				<Br />
			</CharacterStyleRange>
			<CharacterStyleRange AppliedCharacterStyle="CharacterStyle/$ID/[No character style]">
				<Br />
				<Content>Reflections</Content>
				<Br />
			</CharacterStyleRange>
			<CharacterStyleRange AppliedCharacterStyle="CharacterStyle/$ID/[No character style]" FontStyle="Italic">
				<Content>George W. Spasyk</Content>
			</CharacterStyleRange>
		</ParagraphStyleRange>
	</Story>
</idPkg:Story>
